defter.py
defter/__init__.py
defter/defter.py
defter/defter_tr_TR.qm
defter/canta/__init__.py
defter/canta/action.py
defter/canta/arac.py
defter/canta/comboBox.py
defter/canta/dockWidget.py
defter/canta/ekranKutuphane.py
defter/canta/fontComboBox.py
defter/canta/htmlParsers.py
defter/canta/icons_rc.py
defter/canta/komutPenceresi.py
defter/canta/lineEdit.py
defter/canta/listWidgetItem.py
defter/canta/lutfenBekleyin.py
defter/canta/pdfyiResmeCevirPenceresi.py
defter/canta/printPreviewDialog.py
defter/canta/pushButton.py
defter/canta/renkCubuguVeSayiKutusu.py
defter/canta/renkSecici.py
defter/canta/renkSecmeDugmesi.py
defter/canta/sahneKutuphane.py
defter/canta/scene.py
defter/canta/selectionQueue.py
defter/canta/shared.py
defter/canta/slider.py
defter/canta/sliderDoubleWithDoubleSpinBox.py
defter/canta/sliderRenk.py
defter/canta/spinBoxlar.py
defter/canta/syntaxHighlighter.py
defter/canta/tabBar.py
defter/canta/tabWidget.py
defter/canta/threadWorkers.py
defter/canta/toolBar.py
defter/canta/treeModel.py
defter/canta/treeSayfa.py
defter/canta/treeView.py
defter/canta/treeWidget.py
defter/canta/undoRedoFonksiyonlar.py
defter/canta/undoRedoSiniflar.py
defter/canta/videoyuResmeCevirPenceresi.py
defter/canta/view.py
defter/canta/with_signals_updates_blocked.py
defter/canta/altyazi/srt_ayikla.py
defter/canta/nesneler/__init__.py
defter/canta/nesneler/base.py
defter/canta/nesneler/dosya.py
defter/canta/nesneler/ellipse.py
defter/canta/nesneler/group.py
defter/canta/nesneler/image.py
defter/canta/nesneler/kutuphane_nesnesi.py
defter/canta/nesneler/line.py
defter/canta/nesneler/mirrorLine.py
defter/canta/nesneler/path.py
defter/canta/nesneler/rect.py
defter/canta/nesneler/tempTextItem.py
defter/canta/nesneler/text.py
defter/canta/nesneler/video.py
defter/canta/nesneler/web.py
defter/canta/nesneler/yuvarlakFircaBoyutu.py
defter/canta/yanBolme/__init__.py
defter/canta/yanBolme/dikeyDugme.py
defter/canta/yanBolme/dikeyEtiket.py
defter/canta/yanBolme/kenarBoyut.py
defter_argekod-0.97.0.dist-info/LICENSE
defter_argekod-0.97.0.dist-info/METADATA
defter_argekod-0.97.0.dist-info/WHEEL
defter_argekod-0.97.0.dist-info/entry_points.txt
defter_argekod-0.97.0.dist-info/top_level.txt
defter_argekod-0.97.0.dist-info/RECORD
