Metadata-Version: 2.1
Name: defter-argekod
Version: 0.97.0
Summary: Görsel bir not tutma uygulaması. (A visual note-taking app.)
Author: argekod
License: GNU General Public License v3 (GPLv3)
Project-URL: Homepage, https://github.com/erdincyz/defter
Project-URL: Issues, https://github.com/erdincyz/defter/issues
Keywords: note taking,freeform,drawing,visual,graphics,lighttable,html generator,PDF generator,PySide6
Classifier: Development Status :: 3 - Alpha
Classifier: Programming Language :: Python :: 3 :: Only
Classifier: License :: OSI Approved :: GNU General Public License v3 (GPLv3)
Classifier: Natural Language :: Turkish
Classifier: Natural Language :: English
Classifier: Operating System :: OS Independent
Classifier: Environment :: X11 Applications :: Qt
Classifier: Environment :: MacOS X
Classifier: Environment :: Win32 (MS Windows)
Classifier: Intended Audience :: Education
Classifier: Intended Audience :: End Users/Desktop
Classifier: Topic :: Education
Classifier: Topic :: Multimedia :: Graphics
Requires-Python: >=3.8
License-File: LICENSE
Requires-Dist: PySide6
